{
    "username": "STUDENTS ANSWER HERE",
    "name": "STUDENTS ANSWER HERE",
    "question_1": "STUDENTS ANSWER HERE",
    "question_2": "STUDENTS ANSWER HERE",
    "question_3": "STUDENTS ANSWER HERE",
    "question_4": "STUDENTS ANSWER HERE",
    "question_5": "STUDENTS ANSWER HERE",
    "question_6": "STUDENTS ANSWER HERE",
    "question_7": "STUDENTS ANSWER HERE",
    "question_8": "STUDENTS ANSWER HERE",
    "question_9": "STUDENTS ANSWER HERE",
    "question_10": "STUDENTS ANSWER HERE",
    "question_11": "STUDENTS ANSWER HERE",
    "question_12": "STUDENTS ANSWER HERE",
    "question_13": "STUDENTS ANSWER HERE",
    "question_14": "STUDENTS ANSWER HERE",
    "question_15": "STUDENTS ANSWER HERE",
    "question_16": "STUDENTS ANSWER HERE",
    "question_17": "STUDENTS ANSWER HERE",
    "question_18": "STUDENTS ANSWER HERE",
    "question_19": "STUDENTS ANSWER HERE",
    "question_20": "STUDENTS ANSWER HERE",
    "AND_0_0": "STUDENTS ANSWER HERE either 0 or 1",
    "AND_0_1": "STUDENTS ANSWER HERE either 0 or 1",
    "AND_1_0": "STUDENTS ANSWER HERE either 0 or 1",
    "AND_1_1": "STUDENTS ANSWER HERE either 0 or 1",
    "XOR_0_0": "STUDENTS ANSWER HERE either 0 or 1",
    "XOR_0_1": "STUDENTS ANSWER HERE either 0 or 1",
    "XOR_1_0": "STUDENTS ANSWER HERE either 0 or 1",
    "XOR_1_1": "STUDENTS ANSWER HERE either 0 or 1",
    "NAND_0_0": "STUDENTS ANSWER HERE either 0 or 1",
    "NAND_0_1": "STUDENTS ANSWER HERE either 0 or 1",
    "NAND_1_0": "STUDENTS ANSWER HERE either 0 or 1",
    "NAND_1_1": "STUDENTS ANSWER HERE either 0 or 1",
    "NOR_0_0": "STUDENTS ANSWER HERE either 0 or 1",
    "NOR_0_1": "STUDENTS ANSWER HERE either 0 or 1",
    "NOR_1_0": "STUDENTS ANSWER HERE either 0 or 1",
    "NOR_1_1": "STUDENTS ANSWER HERE either 0 or 1"
}
